odoo/addons/website_sale_order_shipping_modification/README.rst
odoo/addons/website_sale_order_shipping_modification/__init__.py
odoo/addons/website_sale_order_shipping_modification/__manifest__.py
odoo/addons/website_sale_order_shipping_modification/controllers/__init__.py
odoo/addons/website_sale_order_shipping_modification/controllers/main.py
odoo/addons/website_sale_order_shipping_modification/controllers/portal.py
odoo/addons/website_sale_order_shipping_modification/i18n/it.po
odoo/addons/website_sale_order_shipping_modification/i18n/website_sale_order_shipping_modification.pot
odoo/addons/website_sale_order_shipping_modification/models/__init__.py
odoo/addons/website_sale_order_shipping_modification/models/website.py
odoo/addons/website_sale_order_shipping_modification/readme/CONTRIBUTORS.md
odoo/addons/website_sale_order_shipping_modification/readme/DESCRIPTION.md
odoo/addons/website_sale_order_shipping_modification/readme/USAGE.md
odoo/addons/website_sale_order_shipping_modification/static/description/icon.png
odoo/addons/website_sale_order_shipping_modification/static/description/index.html
odoo/addons/website_sale_order_shipping_modification/static/src/js/hide_header_footer.esm.js
odoo/addons/website_sale_order_shipping_modification/views/sale_portal_templates.xml
odoo/addons/website_sale_order_shipping_modification/views/website_sale_templates.xml
odoo_addon_website_sale_order_shipping_modification-18.0.1.0.0.3.dist-info/METADATA
odoo_addon_website_sale_order_shipping_modification-18.0.1.0.0.3.dist-info/WHEEL
odoo_addon_website_sale_order_shipping_modification-18.0.1.0.0.3.dist-info/top_level.txt
odoo_addon_website_sale_order_shipping_modification-18.0.1.0.0.3.dist-info/RECORD
